timetools/__init__.py
timetools/timeutil.py
python_timetools-1.0.3.dist-info/LICENSE
python_timetools-1.0.3.dist-info/METADATA
python_timetools-1.0.3.dist-info/WHEEL
python_timetools-1.0.3.dist-info/top_level.txt
python_timetools-1.0.3.dist-info/RECORD
