Metadata-Version: 2.1
Name: python-timetools
Version: 1.0.3
Summary: python time tools
Home-page: https://github.com/xuguox/timetools
Author: neason
Author-email: xgx93610@gmail.com
License: MIT
Project-URL: Source, https://github.com/xuguox/timetools
Classifier: Programming Language :: Python :: 3
Classifier: License :: OSI Approved :: MIT License
Classifier: Operating System :: OS Independent
Requires-Python: >=3.7.0
License-File: LICENSE
Requires-Dist: requests
